secheaders/__init__.py
secheaders/__main__.py
secheaders/cmd_utils.py
secheaders/constants.py
secheaders/eval_utils.py
secheaders/exceptions.py
secheaders/secheaders.py
secheaders/webclient.py
secheaders-0.2.0.dist-info/METADATA
secheaders-0.2.0.dist-info/WHEEL
secheaders-0.2.0.dist-info/entry_points.txt
secheaders-0.2.0.dist-info/licenses/LICENSE
secheaders-0.2.0.dist-info/RECORD
