Metadata-Version: 2.4
Name: secheaders
Version: 0.2.0
Summary: Scan HTTP security headers
Project-URL: Homepage, https://github.com/juerkkil/secheaders
Project-URL: Issues, https://github.com/juerkkil/secheaders/issues
Project-URL: Repository, https://github.com/juerkkil/secheaders
Author-email: Jussi-Pekka Erkkilä <jp.erkkila@gmail.com>
Maintainer-email: Jussi-Pekka Erkkilä <jp.erkkila@gmail.com>
License-File: LICENSE
Keywords: security,web
Classifier: Development Status :: 4 - Beta
Classifier: Environment :: Console
Classifier: Intended Audience :: Developers
Classifier: Intended Audience :: System Administrators
Classifier: License :: OSI Approved :: MIT License
Classifier: Programming Language :: Python
Classifier: Topic :: Internet :: WWW/HTTP
Classifier: Topic :: Security
Requires-Python: >=3.8
